<?xml version="1.0" encoding="UTF-8"?>
<GenRun Id="impl_1" LaunchPart="xc7z010clg400-1" LaunchTime="1500516544">
  <File Type="PLACE-DCP" Name="adc_triger_placed.dcp"/>
  <File Type="PA-DCP" Name="adc_triger.dcp"/>
  <File Type="ROUTE-PWR-RPX" Name="adc_triger_power_routed.rpx"/>
  <File Type="PA-TCL" Name="adc_triger.tcl"/>
  <File Type="INIT-TIMING" Name="adc_triger_timing_summary_init.rpt"/>
  <File Type="OPT-METHODOLOGY-DRC" Name="adc_triger_methodology_drc_opted.rpt"/>
  <File Type="RDI-RDI" Name="adc_triger.vdi"/>
  <File Type="OPT-DCP" Name="adc_triger_opt.dcp"/>
  <File Type="OPT-HWDEF" Name="adc_triger.hwdef"/>
  <File Type="OPT-DRC" Name="adc_triger_drc_opted.rpt"/>
  <File Type="OPT-TIMING" Name="adc_triger_timing_summary_opted.rpt"/>
  <File Type="PWROPT-DCP" Name="adc_triger_pwropt.dcp"/>
  <File Type="PWROPT-DRC" Name="adc_triger_drc_pwropted.rpt"/>
  <File Type="PWROPT-TIMING" Name="adc_triger_timing_summary_pwropted.rpt"/>
  <File Type="PLACE-IO" Name="adc_triger_io_placed.rpt"/>
  <File Type="PLACE-CLK" Name="adc_triger_clock_utilization_placed.rpt"/>
  <File Type="PLACE-UTIL" Name="adc_triger_utilization_placed.rpt"/>
  <File Type="PLACE-UTIL-PB" Name="adc_triger_utilization_placed.pb"/>
  <File Type="PLACE-CTRL" Name="adc_triger_control_sets_placed.rpt"/>
  <File Type="PLACE-SIMILARITY" Name="adc_triger_incremental_reuse_placed.rpt"/>
  <File Type="PLACE-PRE-SIMILARITY" Name="adc_triger_incremental_reuse_pre_placed.rpt"/>
  <File Type="PLACE-TIMING" Name="adc_triger_timing_summary_placed.rpt"/>
  <File Type="POSTPLACE-PWROPT-DCP" Name="adc_triger_postplace_pwropt.dcp"/>
  <File Type="POSTPLACE-PWROPT-TIMING" Name="adc_triger_timing_summary_postplace_pwropted.rpt"/>
  <File Type="PHYSOPT-DCP" Name="adc_triger_physopt.dcp"/>
  <File Type="PHYSOPT-DRC" Name="adc_triger_drc_physopted.rpt"/>
  <File Type="PHYSOPT-TIMING" Name="adc_triger_timing_summary_physopted.rpt"/>
  <File Type="ROUTE-ERROR-DCP" Name="adc_triger_routed_error.dcp"/>
  <File Type="ROUTE-DCP" Name="adc_triger_routed.dcp"/>
  <File Type="ROUTE-BLACKBOX-DCP" Name="adc_triger_routed_bb.dcp"/>
  <File Type="ROUTE-DRC" Name="adc_triger_drc_routed.rpt"/>
  <File Type="ROUTE-DRC-PB" Name="adc_triger_drc_routed.pb"/>
  <File Type="ROUTE-DRC-RPX" Name="adc_triger_drc_routed.rpx"/>
  <File Type="BG-BIN" Name="adc_triger.bin"/>
  <File Type="ROUTE-METHODOLOGY-DRC" Name="adc_triger_methodology_drc_routed.rpt"/>
  <File Type="BG-DRC" Name="adc_triger.drc"/>
  <File Type="ROUTE-METHODOLOGY-DRC-RPX" Name="adc_triger_methodology_drc_routed.rpx"/>
  <File Type="BITSTR-MSK" Name="adc_triger.msk"/>
  <File Type="ROUTE-METHODOLOGY-DRC-PB" Name="adc_triger_methodology_drc_routed.pb"/>
  <File Type="BG-BGN" Name="adc_triger.bgn"/>
  <File Type="ROUTE-PWR" Name="adc_triger_power_routed.rpt"/>
  <File Type="ROUTE-PWR-SUM" Name="adc_triger_power_summary_routed.pb"/>
  <File Type="ROUTE-STATUS" Name="adc_triger_route_status.rpt"/>
  <File Type="ROUTE-STATUS-PB" Name="adc_triger_route_status.pb"/>
  <File Type="ROUTE-TIMINGSUMMARY" Name="adc_triger_timing_summary_routed.rpt"/>
  <File Type="ROUTE-TIMING-PB" Name="adc_triger_timing_summary_routed.pb"/>
  <File Type="ROUTE-TIMING-RPX" Name="adc_triger_timing_summary_routed.rpx"/>
  <File Type="ROUTE-SIMILARITY" Name="adc_triger_incremental_reuse_routed.rpt"/>
  <File Type="ROUTE-CLK" Name="adc_triger_clock_utilization_routed.rpt"/>
  <File Type="POSTROUTE-PHYSOPT-DCP" Name="adc_triger_postroute_physopt.dcp"/>
  <File Type="POSTROUTE-PHYSOPT-BLACKBOX-DCP" Name="adc_triger_postroute_physopt_bb.dcp"/>
  <File Type="POSTROUTE-PHYSOPT-TIMING" Name="adc_triger_timing_summary_postroute_physopted.rpt"/>
  <File Type="POSTROUTE-PHYSOPT-TIMING-PB" Name="adc_triger_timing_summary_postroute_physopted.pb"/>
  <File Type="POSTROUTE-PHYSOPT-TIMING-RPX" Name="adc_triger_timing_summary_postroute_physopted.rpx"/>
  <File Type="BG-BIT" Name="adc_triger.bit"/>
  <File Type="BITSTR-RBT" Name="adc_triger.rbt"/>
  <File Type="BITSTR-NKY" Name="adc_triger.nky"/>
  <File Type="BITSTR-BMM" Name="adc_triger_bd.bmm"/>
  <File Type="BITSTR-MMI" Name="adc_triger.mmi"/>
  <File Type="BITSTR-SYSDEF" Name="adc_triger.sysdef"/>
  <File Type="WBT-USG" Name="usage_statistics_webtalk.html"/>
  <FileSet Name="sources" Type="DesignSrcs" RelSrcDir="$PSRCDIR/sources_1">
    <Filter Type="Srcs"/>
    <File Path="$PSRCDIR/sources_1/new/adc_triger.v">
      <FileInfo>
        <Attr Name="UsedIn" Val="synthesis"/>
        <Attr Name="UsedIn" Val="implementation"/>
        <Attr Name="UsedIn" Val="simulation"/>
      </FileInfo>
    </File>
    <Config>
      <Option Name="DesignMode" Val="RTL"/>
      <Option Name="TopModule" Val="adc_triger"/>
      <Option Name="TopAutoSet" Val="TRUE"/>
    </Config>
  </FileSet>
  <FileSet Name="constrs_in" Type="Constrs" RelSrcDir="$PSRCDIR/constrs_1">
    <Filter Type="Constrs"/>
    <File Path="$PSRCDIR/constrs_1/new/trig_test.xdc">
      <FileInfo>
        <Attr Name="UsedIn" Val="synthesis"/>
        <Attr Name="UsedIn" Val="implementation"/>
      </FileInfo>
    </File>
    <Config>
      <Option Name="TargetConstrsFile" Val="$PSRCDIR/constrs_1/new/trig_test.xdc"/>
      <Option Name="ConstrsType" Val="XDC"/>
    </Config>
  </FileSet>
  <Strategy Version="1" Minor="2">
    <StratHandle Name="Vivado Implementation Defaults" Flow="Vivado Implementation 2017"/>
    <Step Id="init_design"/>
    <Step Id="opt_design"/>
    <Step Id="power_opt_design"/>
    <Step Id="place_design"/>
    <Step Id="post_place_power_opt_design"/>
    <Step Id="phys_opt_design"/>
    <Step Id="route_design"/>
    <Step Id="post_route_phys_opt_design"/>
    <Step Id="write_bitstream"/>
  </Strategy>
</GenRun>
